garpunauth/__init__.py
garpunauth/_default.py
garpunauth/client.py
garpunauth/exceptions.py
garpunauth/flow.py
garpunauth/info.py
garpunauth-0.0.7.dist-info/LICENSE
garpunauth-0.0.7.dist-info/METADATA
garpunauth-0.0.7.dist-info/WHEEL
garpunauth-0.0.7.dist-info/top_level.txt
garpunauth-0.0.7.dist-info/RECORD
