Metadata-Version: 2.1
Name: garpunauth
Version: 0.0.7
Summary: Garpun Authentication Library
Home-page: https://github.com/garpun/garpun-auth-library-python
Author: Garpun Cloud
Author-email: support@garpun.com
License: Apache 2.0
Platform: UNKNOWN
Classifier: Operating System :: OS Independent
Classifier: Programming Language :: Python
Classifier: Programming Language :: Python :: 3.6
Classifier: Programming Language :: Python :: 3.7
Classifier: Programming Language :: Python :: 3 :: Only
Requires-Python: >=3.5
Requires-Dist: oauth2client
